interface/__init__.py
french_interface-1.0.0.dist-info/LICENSE
french_interface-1.0.0.dist-info/METADATA
french_interface-1.0.0.dist-info/WHEEL
french_interface-1.0.0.dist-info/top_level.txt
french_interface-1.0.0.dist-info/RECORD
