Metadata-Version: 2.1
Name: french-interface
Version: 1.0.0
Summary: Infos des interfaces réseau de Windows
Home-page: https://lassainora.fr/librairies/interface
Author: Axelle Viandier
Author-email: axelleviandier@lassainora.fr
Project-URL: Bug Tracker, https://github.com/LassaInora/Interface/issues
Classifier: Natural Language :: French
Classifier: Programming Language :: Python :: 3.10
Classifier: License :: OSI Approved :: GNU General Public License v3 (GPLv3)
Classifier: Operating System :: Microsoft :: Windows
Requires-Python: >=3.10
License-File: LICENSE
